lulebo.py
lulebocli-0.1.3.dist-info/DESCRIPTION.rst
lulebocli-0.1.3.dist-info/METADATA
lulebocli-0.1.3.dist-info/RECORD
lulebocli-0.1.3.dist-info/WHEEL
lulebocli-0.1.3.dist-info/entry_points.txt
lulebocli-0.1.3.dist-info/metadata.json
lulebocli-0.1.3.dist-info/top_level.txt
