Metadata-Version: 2.0
Name: lulebocli
Version: 0.1.3
Summary: CLI tool to interact with the Lulebo API
Home-page: https://github.com/ashlaban/lulebo-api
Author: Kim Albertsson
Author-email: kim@ash.nu
License: UNKNOWN
Keywords: lulebo api cli
Platform: UNKNOWN
Classifier: Development Status :: 3 - Alpha
Classifier: Environment :: Console
Classifier: Intended Audience :: End Users/Desktop
Classifier: Topic :: Home Automation
Classifier: Topic :: Utilities
Classifier: License :: OSI Approved :: GNU General Public License v3 (GPLv3)
Classifier: Programming Language :: Python :: 2
Classifier: Programming Language :: Python :: 2.7
Classifier: Programming Language :: Python :: 3
Classifier: Programming Language :: Python :: 3.6
Requires-Dist: keyring
Requires-Dist: requests
